{
  "category": "Boys Waist Coat",
  "params": {
    "rf": {
      "n_estimators": 297,
      "max_depth": 18,
      "min_samples_split": 6,
      "min_samples_leaf": 3,
      "max_features": null
    },
    "xgb": {
      "n_estimators": 192,
      "max_depth": 5,
      "learning_rate": 0.010177679216112151,
      "subsample": 0.7110023605597777,
      "colsample_bytree": 0.8637329469640875,
      "reg_alpha": 0.7546748295193659,
      "reg_lambda": 0.531593510518449
    },
    "lgb": {
      "n_estimators": 229,
      "max_depth": 10,
      "learning_rate": 0.22299724799747747,
      "subsample": 0.6609230930887319,
      "colsample_bytree": 0.6537551176503092,
      "reg_alpha": 0.44645025498929336,
      "reg_lambda": 0.5894268695612733
    }
  },
  "performance": 0.23654913956253046,
  "samples": 86,
  "feature_columns": [
    "total_sales",
    "days_since_first_sale",
    "days_since_last_sale",
    "product_lifecycle_days",
    "sales_velocity",
    "recent_velocity",
    "lifecycle_velocity",
    "sales_recency_score",
    "sales_frequency_score",
    "is_new_product",
    "is_mature_product",
    "is_declining",
    "category_sku_count",
    "category_total_sales",
    "category_avg_sales_per_sku",
    "category_market_share",
    "category_competition",
    "category_saturation",
    "category_performance_tier_encoded",
    "size_category_popularity",
    "size_category_rank",
    "color_total_sales",
    "color_trend_score",
    "total_inventory_movement",
    "avg_inventory_movement",
    "std_inventory_movement",
    "inventory_transactions",
    "days_since_first_inventory",
    "days_since_last_inventory",
    "total_stockout_qty",
    "stockout_frequency",
    "total_returns",
    "return_frequency",
    "season_1_sales",
    "season_2_sales",
    "season_3_sales",
    "season_4_sales",
    "Size Name_first_encoded",
    "Size Code_first_encoded",
    "Color Name_first_encoded",
    "Color Code_first_encoded",
    "Category_first_encoded",
    "Gender_first_encoded",
    "Season_first_encoded",
    "LineItem_first_encoded"
  ]
}